mups/__init__.py
mups/__main__.py
mups/generator.py
mups/templates/README_TEMPLATE.md
mups/templates/boot.py
mups/templates/conf.py
mups/templates/gitignore
mups/templates/venv.sh
mups-0.1.3.dist-info/licenses/LICENSE
mups-0.1.3.dist-info/METADATA
mups-0.1.3.dist-info/WHEEL
mups-0.1.3.dist-info/top_level.txt
mups-0.1.3.dist-info/RECORD
