Metadata-Version: 2.4
Name: mups
Version: 0.1.3
Summary: Multi Use PipelineS: reproducible job templates for Python projects
Author: Alex Mihnev
Project-URL: Repository, https://gitlab.com/mhnv/mups
Requires-Python: >=3.10
License-File: LICENSE
Dynamic: license-file
